code_hacks_calculator_test/__init__.py
codehackscalculatortestpkg-0.0.1.dist-info/LICENSE.txt
codehackscalculatortestpkg-0.0.1.dist-info/METADATA
codehackscalculatortestpkg-0.0.1.dist-info/WHEEL
codehackscalculatortestpkg-0.0.1.dist-info/top_level.txt
codehackscalculatortestpkg-0.0.1.dist-info/RECORD
